{"GlobalPropertiesHash":"CPrTEh/svyb6AMNi/GUnExBLGRHb0dUJYtLjfdDsCuc=","FingerprintPatternsHash":"gq3WsqcKBUGTSNle7RKKyXRIwh7M8ccEqOqYvIzoM04=","PropertyOverridesHash":"8ZRc1sGeVrPBx4lD717BgRaQekyh78QKV9SKsdt638U=","InputHashes":["dV5C84l\u002BnOSbqBTaimF1AROpe9Sl3jzjuAYU7V2BLJE=","bNlNBzpPA2y0ClyE8\u002BOrNPEtmEefCvQUyqMo\u002BVrB8Wc=","EHnc0g8VIUgXh5FWUYoi9iaGqdmEgE47hyX0VTUCKzY="],"CachedAssets":{"dV5C84l\u002BnOSbqBTaimF1AROpe9Sl3jzjuAYU7V2BLJE=":{"Identity":"C:\\Users\\ssasg\\source\\repos\\ChatApp\\Backend\\ChatApp\\wwwroot\\images\\user-image.jpg","SourceId":"ChatApp","SourceType":"Discovered","ContentRoot":"C:\\Users\\ssasg\\source\\repos\\ChatApp\\Backend\\ChatApp\\wwwroot\\","BasePath":"_content/ChatApp","RelativePath":"images/user-image#[.{fingerprint}]?.jpg","AssetKind":"All","AssetMode":"All","AssetRole":"Primary","AssetMergeBehavior":null,"AssetMergeSource":"","RelatedAsset":null,"AssetTraitName":null,"AssetTraitValue":null,"Fingerprint":"3totyi7v8j","Integrity":"KcPMy5bbDNKEQFXik\u002BYXkn8un3zo6T9QSXvTekixIKw=","CopyToOutputDirectory":"Never","CopyToPublishDirectory":"PreserveNewest","OriginalItemSpec":"wwwroot\\images\\user-image.jpg","FileLength":2978,"LastWriteTime":"2025-09-23T06:52:44.1606652+00:00"}},"CachedCopyCandidates":{}}